gempy/__init__.py
gempy/_version.py
gempy/config.py
gempy/optional_dependencies.py
gempy/API/__init__.py
gempy/API/_version.py
gempy/API/compute_API.py
gempy/API/examples_generator.py
gempy/API/faults_API.py
gempy/API/grid_API.py
gempy/API/implicit_functions.py
gempy/API/initialization_API.py
gempy/API/io_API.py
gempy/API/map_stack_to_surfaces_API.py
gempy/API/gp2_gp3_compatibility/__init__.py
gempy/API/gp2_gp3_compatibility/gp3_to_gp2_input.py
gempy/API/gp2_gp3_compatibility/gp3_to_gp2_output.py
gempy/core/__init__.py
gempy/core/color_generator.py
gempy/core/data/DEP_xsolution.py
gempy/core/data/__init__.py
gempy/core/data/_data_points_helpers.py
gempy/core/data/core_utils.py
gempy/core/data/enumerators.py
gempy/core/data/gempy_engine_config.py
gempy/core/data/geo_model.py
gempy/core/data/grid.py
gempy/core/data/importer_helper.py
gempy/core/data/options.py
gempy/core/data/orientations.py
gempy/core/data/structural_element.py
gempy/core/data/structural_frame.py
gempy/core/data/structural_group.py
gempy/core/data/surface_points.py
gempy/core/data/encoders/__init__.py
gempy/core/data/encoders/binary_encoder.py
gempy/core/data/encoders/converters.py
gempy/core/data/encoders/json_geomodel_encoder.py
gempy/core/data/grid_modules/__init__.py
gempy/core/data/grid_modules/custom_grid.py
gempy/core/data/grid_modules/diamond_square.py
gempy/core/data/grid_modules/regular_grid.py
gempy/core/data/grid_modules/sections_grid.py
gempy/core/data/grid_modules/topography.py
gempy/modules/__init__.py
gempy/modules/advance_pile/__init__.py
gempy/modules/advance_pile/strat_definition.py
gempy/modules/custom_implicit_functions/__init__.py
gempy/modules/custom_implicit_functions/ellipsoid_implicit_function.py
gempy/modules/data_manipulation/__init__.py
gempy/modules/data_manipulation/_engine_factory.py
gempy/modules/data_manipulation/manipulate_points.py
gempy/modules/data_manipulation/manipulate_structural_frame.py
gempy/modules/data_manipulation/orientations_from_surface_points.py
gempy-2025.2.0.dist-info/licenses/AUTHORS.rst
gempy-2025.2.0.dist-info/licenses/LICENSE
gempy-2025.2.0.dist-info/METADATA
gempy-2025.2.0.dist-info/WHEEL
gempy-2025.2.0.dist-info/top_level.txt
gempy-2025.2.0.dist-info/RECORD
