Metadata-Version: 2.4
Name: gempy
Version: 2025.2.0
Summary: An Open-source, Python-based 3-D structural geological modeling software.
Home-page: https://github.com/cgre-aachen/gempy
Author: Miguel de la Varga, Alexander Zimmerman, Elisa Heim, Alexander Schaaf, Fabian Stamm, Florian Wellmann, Jan Niederau, Andrew Annex
Author-email: gempy@terranigma-solutions.com
License: EUPL-1.2
Keywords: geology,3-D modeling,structural geology,uncertainty
Classifier: Development Status :: 5 - Production/Stable
Classifier: Intended Audience :: Developers
Classifier: License :: OSI Approved :: European Union Public Licence 1.2 (EUPL 1.2)
Classifier: Operating System :: OS Independent
Classifier: Programming Language :: Python :: 3
Classifier: Programming Language :: Python :: 3.10
Classifier: Programming Language :: Python :: 3.11
Classifier: Programming Language :: Python :: 3.12
License-File: LICENSE
License-File: AUTHORS.rst
Requires-Dist: gempy_engine<2025.3.0,>=2025.2.0dev0
Provides-Extra: opt
Requires-Dist: gempy_engine<2025.3.0,>=2025.2.0dev0; extra == "opt"
Requires-Dist: gempy_viewer~=2025.1.0; extra == "opt"
Requires-Dist: pandas; extra == "opt"
Requires-Dist: gempy_plugins; extra == "opt"
Requires-Dist: pooch; extra == "opt"
Requires-Dist: scipy; extra == "opt"
Requires-Dist: scikit-image; extra == "opt"
Provides-Extra: base
Requires-Dist: gempy_engine<2025.3.0,>=2025.2.0dev0; extra == "base"
Requires-Dist: gempy_viewer~=2025.1.0; extra == "base"
Requires-Dist: pandas; extra == "base"
Dynamic: author
Dynamic: author-email
Dynamic: classifier
Dynamic: description
Dynamic: description-content-type
Dynamic: home-page
Dynamic: keywords
Dynamic: license
Dynamic: license-file
Dynamic: provides-extra
Dynamic: requires-dist
Dynamic: summary
